pdf_segregation/__init__.py
pdf_segregation/pdf_classifier.py
pdf_segregation-2.0.2.dist-info/METADATA
pdf_segregation-2.0.2.dist-info/WHEEL
pdf_segregation-2.0.2.dist-info/top_level.txt
pdf_segregation-2.0.2.dist-info/RECORD
