Metadata-Version: 2.1
Name: pdf-segregation
Version: 2.0.2
Summary: This module will return whether PDF is Digital, Non-Digital or Mixed.
Home-page: UNKNOWN
Author: Kishan Tongrao
Author-email: kishan.tongs@gmail.com
License: UNKNOWN
Platform: UNKNOWN
Classifier: Development Status :: 1 - Planning
Classifier: Intended Audience :: Developers
Classifier: Programming Language :: Python :: 3
Classifier: Operating System :: Unix
Classifier: Operating System :: MacOS :: MacOS X
Classifier: Operating System :: Microsoft :: Windows
Requires-Dist: PyPDF2
